chaps_lzf.cpython-36m-x86_64-linux-gnu.so
chaps_lzf-0.0.1.dist-info/METADATA
chaps_lzf-0.0.1.dist-info/WHEEL
chaps_lzf-0.0.1.dist-info/RECORD
chaps_lzf-0.0.1.dist-info/top_level.txt
